Metadata-Version: 2.1
Name: EasyLiker
Version: 1.0
Summary: EasyLiker python api Github - https://github.com/Badsnus/EasyLiker-Pyhon-api
Home-page: https://github.com/Badsnus/EasyLiker-Pyhon-api
Author-email: Badsnus <badsnus@mail.ru>
License: UNKNOWN
Platform: UNKNOWN
